pygithubactions/__init__.py
pygithubactions/context/__init__.py
pygithubactions/context/context.py
pygithubactions/core/__init__.py
pygithubactions/core/command.py
pygithubactions/core/core.py
pygithubactions/core/file_command.py
pygithubactions/core/path_utils.py
pygithubactions/core/utils.py
pygithubactions-0.1.5.dist-info/METADATA
pygithubactions-0.1.5.dist-info/WHEEL
pygithubactions-0.1.5.dist-info/licenses/LICENSE
pygithubactions-0.1.5.dist-info/RECORD
