Metadata-Version: 2.1
Name: pygithubactions
Version: 0.1.5
Summary: Github actions core library implemented in python
Project-URL: Homepage, https://github.com/lestex/pygithubactions.git
Project-URL: Source, https://github.com/lestex/pygithubactions.git
Author-email: Andrey Larin <lestex@gmail.com>
License-File: LICENSE
Keywords: pygithubactions
Classifier: Intended Audience :: Developers
Classifier: License :: OSI Approved :: MIT License
Classifier: Programming Language :: Python :: 3 :: Only
Classifier: Programming Language :: Python :: 3.8
Classifier: Programming Language :: Python :: 3.9
Classifier: Programming Language :: Python :: 3.10
Classifier: Programming Language :: Python :: 3.11
Classifier: Topic :: Software Development :: Build Tools
Requires-Python: >=3.8
